wyoming_snowboy/__init__.py
wyoming_snowboy/__main__.py
wyoming_snowboy/data/alexa.umdl
wyoming_snowboy/data/hey_extreme.umdl
wyoming_snowboy/data/jarvis.umdl
wyoming_snowboy/data/neoya.umdl
wyoming_snowboy/data/smart_mirror.umdl
wyoming_snowboy/data/snowboy.umdl
wyoming_snowboy/data/subex.umdl
wyoming_snowboy/data/view_glass.umdl
wyoming_snowboy-1.0.0.dist-info/LICENSE.md
wyoming_snowboy-1.0.0.dist-info/METADATA
wyoming_snowboy-1.0.0.dist-info/WHEEL
wyoming_snowboy-1.0.0.dist-info/top_level.txt
wyoming_snowboy-1.0.0.dist-info/RECORD
