Metadata-Version: 2.1
Name: wyoming-snowboy
Version: 1.0.0
Summary: Wyoming Server for Snowboy
Home-page: http://github.com/rhasspy/wyoming-snowboy
Author: Michael Hansen
Author-email: mike@rhasspy.org
License: MIT
Keywords: rhasspy wyoming snowboy wake word
Classifier: Development Status :: 3 - Alpha
Classifier: Intended Audience :: Developers
Classifier: Topic :: Text Processing :: Linguistic
Classifier: License :: OSI Approved :: MIT License
Classifier: Programming Language :: Python :: 3.7
Classifier: Programming Language :: Python :: 3.8
Classifier: Programming Language :: Python :: 3.9
Classifier: Programming Language :: Python :: 3.10
Classifier: Programming Language :: Python :: 3.11
License-File: LICENSE.md
Requires-Dist: snowboy ==1.2.0b1
Requires-Dist: wyoming ==1.2.0
